nora/__init__.py
nora/client.py
nora/_internal/__init__.py
nora/_internal/decisions.py
nora/_internal/execution_span.py
nora/_internal/utils.py
nora/_internal/anthropic/__init__.py
nora/_internal/anthropic/metadata_builder.py
nora/_internal/anthropic/streaming.py
nora/_internal/anthropic/types.py
nora/_internal/anthropic/utils.py
nora/_internal/gemini/__init__.py
nora/_internal/gemini/metadata_builder.py
nora/_internal/gemini/streaming.py
nora/_internal/gemini/types.py
nora/_internal/gemini/utils.py
nora/_internal/litellm/__init__.py
nora/_internal/litellm/metadata_builder.py
nora/_internal/litellm/streaming.py
nora/_internal/litellm/utils.py
nora/_internal/ollama/__init__.py
nora/_internal/ollama/metadata_builder.py
nora/_internal/ollama/streaming.py
nora/_internal/ollama/token_estimator.py
nora/_internal/ollama/types.py
nora/_internal/ollama/utils.py
nora/_internal/openai/__init__.py
nora/_internal/openai/metadata_builder.py
nora/_internal/openai/streaming.py
nora/_internal/openai/tool_tracer.py
nora/_internal/openai/types.py
nora/_internal/openai/utils.py
nora/_internal/patches/__init__.py
nora/_internal/patches/anthropic_patch.py
nora/_internal/patches/gemini_patch.py
nora/_internal/patches/langgraph_patch.py
nora/_internal/patches/litellm_patch.py
nora/_internal/patches/ollama_patch.py
nora/_internal/patches/openai_patch.py
nora/data_set/__init__.py
nora/prompt/__init__.py
nora_ai-0.2.1.dist-info/METADATA
nora_ai-0.2.1.dist-info/WHEEL
nora_ai-0.2.1.dist-info/top_level.txt
nora_ai-0.2.1.dist-info/RECORD
